translucenttb/__init__.py
translucenttb/blur.py
translucenttb/main.py
translucenttb-0.0.4.dist-info/METADATA
translucenttb-0.0.4.dist-info/WHEEL
translucenttb-0.0.4.dist-info/top_level.txt
translucenttb-0.0.4.dist-info/RECORD
