Metadata-Version: 2.1
Name: translucenttb
Version: 0.0.4
Summary: A python version TranslucentTB
Home-page: https://github.com/littlewhitecloud/TranslucentTB/
Author: littlewhitecloud
